contentrelations/__init__.py
contentrelations/admin.py
contentrelations/apps.py
contentrelations/base.py
contentrelations/generic.py
contentrelations/genericcollection.py
contentrelations/models.py
contentrelations/module_loading.py
contentrelations/registration.py
contentrelations/related.py
contentrelations/serializer.py
contentrelations/settings.py
contentrelations/tests.py
contentrelations/urls.py
contentrelations/views.py
contentrelations/static/contentrelations/js/genericlookup.js
contentrelations/templates/admin/edit_inline/related_resource_inline.html
contentrelations/templatetags/__init__.py
contentrelations/templatetags/resources.py
django_contentrelations-1.4.2.dist-info/DESCRIPTION.rst
django_contentrelations-1.4.2.dist-info/METADATA
django_contentrelations-1.4.2.dist-info/RECORD
django_contentrelations-1.4.2.dist-info/WHEEL
django_contentrelations-1.4.2.dist-info/metadata.json
django_contentrelations-1.4.2.dist-info/pbr.json
django_contentrelations-1.4.2.dist-info/top_level.txt
