Metadata-Version: 2.0
Name: django-contentrelations
Version: 1.4.2
Summary: Allows connecting any object to any other object and unifying the interface between all the objects.
Home-page: http://callowayproject.com/
Author: Corey Oordt
Author-email: webmaster@callowayproject.com
License: UNKNOWN
Platform: UNKNOWN
Classifier: License :: OSI Approved :: Apache Software License
Classifier: Framework :: Django
